[{"neighborhood": "Custer/McDonough/Guice", "occur_time": "15", "longitude": "-84.349969999999999", "latitude": "33.715710000000001", "occur_date": "01/02/2016", "type": "LARCENY-NON VEHICLE", "day": "Sat", "street_address": "1405 MORELAND AVE SE"}, {"neighborhood": "Custer/McDonough/Guice", "occur_time": "03", "longitude": "-84.350070000000002", "latitude": "33.712899999999998", "occur_date": "01/08/2016", "type": "BURGLARY-NONRES", "day": "Fri", "street_address": "1475 MORELAND AVE SE"}, {"neighborhood": "Custer/McDonough/Guice", "occur_time": "", "longitude": "-84.357290000000006", "latitude": "33.710790000000003", "occur_date": "01/11/2016", "type": "AUTO THEFT", "day": "Mon", "street_address": "1605 PONTIAC PL SE"}, {"neighborhood": "Custer/McDonough/Guice", "occur_time": "22", "longitude": "-84.358490000000003", "latitude": "33.709789999999998", "occur_date": "01/09/2016", "type": "BURGLARY-RESIDENCE", "day": "Sat", "street_address": "1940 FISHER RD SE"}, {"neighborhood": "Custer/McDonough/Guice", "occur_time": "15", "longitude": "-84.350040000000007", "latitude": "33.711799999999997", "occur_date": "01/11/2016", "type": "LARCENY-FROM VEHICLE", "day": "Mon", "street_address": "1575 MORELAND AVE SE"}, {"neighborhood": "Custer/McDonough/Guice", "occur_time": "19", "longitude": "-84.355789999999999", "latitude": "33.709879999999998", "occur_date": "01/10/2016", "type": "BURGLARY-RESIDENCE", "day": "Unk", "street_address": "1636 WELLSWOOD DR SE"}, {"neighborhood": "Custer/McDonough/Guice", "occur_time": "11", "longitude": "-84.350080000000005", "latitude": "33.71369", "occur_date": "01/18/2016", "type": "LARCENY-NON VEHICLE", "day": "Mon", "street_address": "1461 MORELAND AVE SE"}, {"neighborhood": "Custer/McDonough/Guice", "occur_time": "16", "longitude": "-84.350089999999994", "latitude": "33.71443", "occur_date": "02/26/2016", "type": "LARCENY-NON VEHICLE", "day": "Fri", "street_address": "1459 MORELAND AVE SE"}, {"neighborhood": "Custer/McDonough/Guice", "occur_time": "18", "longitude": "-84.358869999999996", "latitude": "33.708739999999999", "occur_date": "02/27/2016", "type": "LARCENY-NON VEHICLE", "day": "Unk", "street_address": "840 MCDONOUGH BLVD SE"}, {"neighborhood": "Custer/McDonough/Guice", "occur_time": "18", "longitude": "-84.358490000000003", "latitude": "33.709789999999998", "occur_date": "03/12/2016", "type": "AGG ASSAULT", "day": "Sat", "street_address": "1940 FISHER RD SE"}, {"neighborhood": "Custer/McDonough/Guice", "occur_time": "01", "longitude": "-84.349940000000004", "latitude": "33.709409999999998", "occur_date": "03/17/2016", "type": "AGG ASSAULT", "day": "Thu", "street_address": "1635 MORELAND AVE SE"}, {"neighborhood": "Custer/McDonough/Guice", "occur_time": "19", "longitude": "-84.350089999999994", "latitude": "33.71443", "occur_date": "04/01/2016", "type": "ROBBERY-PEDESTRIAN", "day": "Fri", "street_address": "1459 MORELAND AVE SE"}, {"neighborhood": "Custer/McDonough/Guice", "occur_time": "23", "longitude": "-84.350089999999994", "latitude": "33.71443", "occur_date": "04/01/2016", "type": "ROBBERY-PEDESTRIAN", "day": "Fri", "street_address": "1459 MORELAND AVE SE"}, {"neighborhood": "Custer/McDonough/Guice", "occur_time": "07", "longitude": "-84.352919999999997", "latitude": "33.711309999999997", "occur_date": "04/04/2016", "type": "ROBBERY-PEDESTRIAN", "day": "Mon", "street_address": "1569 WOODLAND AVE SE"}, {"neighborhood": "Custer/McDonough/Guice", "occur_time": "11", "longitude": "-84.358490000000003", "latitude": "33.709789999999998", "occur_date": "04/04/2016", "type": "BURGLARY-RESIDENCE", "day": "Mon", "street_address": "1940 FISHER RD SE"}, {"neighborhood": "Custer/McDonough/Guice", "occur_time": "02", "longitude": "-84.354339999999993", "latitude": "33.707720000000002", "occur_date": "04/14/2016", "type": "BURGLARY-NONRES", "day": "Thu", "street_address": "1041 MORELAND DR SE"}, {"neighborhood": "Custer/McDonough/Guice", "occur_time": "03", "longitude": "-84.351900000000001", "latitude": "33.713760000000001", "occur_date": "04/16/2016", "type": "BURGLARY-RESIDENCE", "day": "Sat", "street_address": "1475 WOODLAND CIR SE"}, {"neighborhood": "Custer/McDonough/Guice", "occur_time": "14", "longitude": "-84.350139999999996", "latitude": "33.714779999999998", "occur_date": "03/27/2016", "type": "LARCENY-NON VEHICLE", "day": "Unk", "street_address": "1455 MORELAND AVE SE"}, {"neighborhood": "Custer/McDonough/Guice", "occur_time": "08", "longitude": "-84.354140000000001", "latitude": "33.708820000000003", "occur_date": "04/26/2016", "type": "LARCENY-NON VEHICLE", "day": "Tue", "street_address": "1051 MORELAND DR SE"}, {"neighborhood": "Custer/McDonough/Guice", "occur_time": "17", "longitude": "-84.358869999999996", "latitude": "33.708739999999999", "occur_date": "04/26/2016", "type": "BURGLARY-NONRES", "day": "Wed", "street_address": "840 MCDONOUGH BLVD SE"}, {"neighborhood": "Custer/McDonough/Guice", "occur_time": "07", "longitude": "-84.353489999999994", "latitude": "33.71405", "occur_date": "04/28/2016", "type": "AUTO THEFT", "day": "Thu", "street_address": "1485 WOODLAND AVE SE"}, {"neighborhood": "Custer/McDonough/Guice", "occur_time": "16", "longitude": "-84.350139999999996", "latitude": "33.714779999999998", "occur_date": "05/03/2016", "type": "LARCENY-NON VEHICLE", "day": "Tue", "street_address": "1455 MORELAND AVE SE"}, {"neighborhood": "Custer/McDonough/Guice", "occur_time": "20", "longitude": "-84.354119999999995", "latitude": "33.708820000000003", "occur_date": "05/04/2016", "type": "AGG ASSAULT", "day": "Wed", "street_address": "1053 MORELAND DR SE"}, {"neighborhood": "Custer/McDonough/Guice", "occur_time": "10", "longitude": "-84.351479999999995", "latitude": "33.71716", "occur_date": "05/06/2016", "type": "BURGLARY-RESIDENCE", "day": "Fri", "street_address": "1350 SUMMER LANE DR SE"}, {"neighborhood": "Custer/McDonough/Guice", "occur_time": "10", "longitude": "-84.349850000000004", "latitude": "33.716090000000001", "occur_date": "05/10/2016", "type": "LARCENY-NON VEHICLE", "day": "Tue", "street_address": "1401 MORELAND AVE SE"}, {"neighborhood": "Custer/McDonough/Guice", "occur_time": "14", "longitude": "-84.349990000000005", "latitude": "33.716450000000002", "occur_date": "05/08/2016", "type": "AUTO THEFT", "day": "Unk", "street_address": "1395 MORELAND AVE SE"}, {"neighborhood": "Custer/McDonough/Guice", "occur_time": "18", "longitude": "-84.350139999999996", "latitude": "33.714779999999998", "occur_date": "05/12/2016", "type": "LARCENY-NON VEHICLE", "day": "Thu", "street_address": "1455 MORELAND AVE SE"}, {"neighborhood": "Custer/McDonough/Guice", "occur_time": "18", "longitude": "-84.350139999999996", "latitude": "33.714779999999998", "occur_date": "05/17/2016", "type": "LARCENY-NON VEHICLE", "day": "Tue", "street_address": "1455 MORELAND AVE SE"}, {"neighborhood": "Custer/McDonough/Guice", "occur_time": "19", "longitude": "-84.350170000000006", "latitude": "33.711129999999997", "occur_date": "05/31/2016", "type": "AUTO THEFT", "day": "Wed", "street_address": "1585 MORELAND AVE SE"}, {"neighborhood": "Custer/McDonough/Guice", "occur_time": "04", "longitude": "-84.357050000000001", "latitude": "33.707880000000003", "occur_date": "06/05/2016", "type": "BURGLARY-RESIDENCE", "day": "Sun", "street_address": "969 WELCH ST SE"}, {"neighborhood": "Custer/McDonough/Guice", "occur_time": "00", "longitude": "-84.349850000000004", "latitude": "33.716090000000001", "occur_date": "06/30/2016", "type": "BURGLARY-NONRES", "day": "Thu", "street_address": "1401 MORELAND AVE SE"}, {"neighborhood": "Custer/McDonough/Guice", "occur_time": "16", "longitude": "-84.35087", "latitude": "33.716410000000003", "occur_date": "06/18/2016", "type": "LARCENY-NON VEHICLE", "day": "Sat", "street_address": "1356 HEIGHTS PARK DR"}, {"neighborhood": "Custer/McDonough/Guice", "occur_time": "20", "longitude": "-84.350139999999996", "latitude": "33.714779999999998", "occur_date": "07/21/2016", "type": "LARCENY-NON VEHICLE", "day": "Thu", "street_address": "1455 MORELAND AVE SE"}, {"neighborhood": "Custer/McDonough/Guice", "occur_time": "16", "longitude": "-84.358490000000003", "latitude": "33.709789999999998", "occur_date": "06/03/2016", "type": "LARCENY-NON VEHICLE", "day": "Unk", "street_address": "1940 FISHER RD SE"}, {"neighborhood": "Custer/McDonough/Guice", "occur_time": "02", "longitude": "-84.351969999999994", "latitude": "33.712490000000003", "occur_date": "08/01/2016", "type": "LARCENY-NON VEHICLE", "day": "Mon", "street_address": "1565 WOODLAND CIR SE"}, {"neighborhood": "Custer/McDonough/Guice", "occur_time": "13", "longitude": "-84.351659999999995", "latitude": "33.714950000000002", "occur_date": "08/02/2016", "type": "LARCENY-NON VEHICLE", "day": "Tue", "street_address": "1125 CUSTER AVE SE"}, {"neighborhood": "Custer/McDonough/Guice", "occur_time": "19", "longitude": "-84.350139999999996", "latitude": "33.714779999999998", "occur_date": "08/08/2016", "type": "LARCENY-NON VEHICLE", "day": "Mon", "street_address": "1455 MORELAND AVE SE"}, {"neighborhood": "Custer/McDonough/Guice", "occur_time": "15", "longitude": "-84.357190000000003", "latitude": "33.707799999999999", "occur_date": "08/14/2016", "type": "ROBBERY-PEDESTRIAN", "day": "Sun", "street_address": "969 WELCH ST SE"}, {"neighborhood": "Custer/McDonough/Guice", "occur_time": "08", "longitude": "-84.350139999999996", "latitude": "33.714779999999998", "occur_date": "08/17/2016", "type": "LARCENY-NON VEHICLE", "day": "Wed", "street_address": "1455 MORELAND AVE SE"}, {"neighborhood": "Custer/McDonough/Guice", "occur_time": "06", "longitude": "-84.358490000000003", "latitude": "33.709789999999998", "occur_date": "08/18/2016", "type": "AGG ASSAULT", "day": "Thu", "street_address": "1940 FISHER RD SE"}, {"neighborhood": "Custer/McDonough/Guice", "occur_time": "15", "longitude": "-84.349630000000005", "latitude": "33.711399999999998", "occur_date": "06/01/2016", "type": "LARCENY-NON VEHICLE", "day": "Unk", "street_address": "1579 MORELAND AVE SE"}, {"neighborhood": "Custer/McDonough/Guice", "occur_time": "20", "longitude": "-84.350089999999994", "latitude": "33.71443", "occur_date": "09/06/2016", "type": "ROBBERY-COMMERCIAL", "day": "Tue", "street_address": "1459 MORELAND AVE SE"}, {"neighborhood": "Custer/McDonough/Guice", "occur_time": "10", "longitude": "-84.349990000000005", "latitude": "33.716450000000002", "occur_date": "09/07/2016", "type": "LARCENY-NON VEHICLE", "day": "Wed", "street_address": "1395 MORELAND AVE SE"}, {"neighborhood": "Custer/McDonough/Guice", "occur_time": "12", "longitude": "-84.359979999999993", "latitude": "33.717280000000002", "occur_date": "09/12/2016", "type": "BURGLARY-RESIDENCE", "day": "Mon", "street_address": "884 CUSTER AVE SE"}, {"neighborhood": "Custer/McDonough/Guice", "occur_time": "14", "longitude": "-84.349850000000004", "latitude": "33.716090000000001", "occur_date": "09/13/2016", "type": "LARCENY-FROM VEHICLE", "day": "Tue", "street_address": "1401 MORELAND AVE SE"}, {"neighborhood": "Custer/McDonough/Guice", "occur_time": "04", "longitude": "-84.35772", "latitude": "33.715380000000003", "occur_date": "09/23/2016", "type": "LARCENY-FROM VEHICLE", "day": "Fri", "street_address": "947 BRUCE CIR SE"}, {"neighborhood": "Custer/McDonough/Guice", "occur_time": "22", "longitude": "-84.35087", "latitude": "33.716410000000003", "occur_date": "09/22/2016", "type": "LARCENY-FROM VEHICLE", "day": "Fri", "street_address": "1356 HEIGHTS PARK DR SE"}, {"neighborhood": "Custer/McDonough/Guice", "occur_time": "00", "longitude": "-84.356740000000002", "latitude": "33.710340000000002", "occur_date": "09/27/2016", "type": "AUTO THEFT", "day": "Tue", "street_address": "1624 PONTIAC PL SE"}, {"neighborhood": "Custer/McDonough/Guice", "occur_time": "15", "longitude": "-84.350080000000005", "latitude": "33.71369", "occur_date": "09/28/2016", "type": "LARCENY-FROM VEHICLE", "day": "Wed", "street_address": "1461 MORELAND AVE SE"}, {"neighborhood": "Custer/McDonough/Guice", "occur_time": "16", "longitude": "-84.356750000000005", "latitude": "33.709229999999998", "occur_date": "09/02/2016", "type": "AUTO THEFT", "day": "Unk", "street_address": "1940 FISHER RD SE"}, {"neighborhood": "Custer/McDonough/Guice", "occur_time": "12", "longitude": "-84.349620000000002", "latitude": "33.713590000000003", "occur_date": "10/07/2016", "type": "AGG ASSAULT", "day": "Fri", "street_address": "1455 MORELAND AVE SE"}, {"neighborhood": "Custer/McDonough/Guice", "occur_time": "17", "longitude": "-84.357190000000003", "latitude": "33.707799999999999", "occur_date": "10/09/2016", "type": "BURGLARY-RESIDENCE", "day": "Sun", "street_address": "969 WELCH ST SE"}, {"neighborhood": "Custer/McDonough/Guice", "occur_time": "20", "longitude": "-84.350089999999994", "latitude": "33.71443", "occur_date": "10/11/2016", "type": "ROBBERY-PEDESTRIAN", "day": "Tue", "street_address": "1459 MORELAND AVE SE"}, {"neighborhood": "Custer/McDonough/Guice", "occur_time": "12", "longitude": "-84.357330000000005", "latitude": "33.708190000000002", "occur_date": "08/12/2016", "type": "LARCENY-NON VEHICLE", "day": "Unk", "street_address": "964 WELCH ST SE"}, {"neighborhood": "Custer/McDonough/Guice", "occur_time": "19", "longitude": "-84.350139999999996", "latitude": "33.714779999999998", "occur_date": "10/13/2016", "type": "LARCENY-FROM VEHICLE", "day": "Thu", "street_address": "1455 MORELAND AVE SE"}, {"neighborhood": "Custer/McDonough/Guice", "occur_time": "00", "longitude": "-84.358869999999996", "latitude": "33.708739999999999", "occur_date": "10/15/2016", "type": "LARCENY-FROM VEHICLE", "day": "Sat", "street_address": "840 MCDONOUGH BLVD SE"}, {"neighborhood": "Custer/McDonough/Guice", "occur_time": "10", "longitude": "-84.350070000000002", "latitude": "33.712899999999998", "occur_date": "10/19/2016", "type": "LARCENY-FROM VEHICLE", "day": "Wed", "street_address": "1475 MORELAND AVE SE"}, {"neighborhood": "Custer/McDonough/Guice", "occur_time": "01", "longitude": "-84.350139999999996", "latitude": "33.714779999999998", "occur_date": "10/20/2016", "type": "ROBBERY-PEDESTRIAN", "day": "Thu", "street_address": "1455 MORELAND AVE SE"}, {"neighborhood": "Custer/McDonough/Guice", "occur_time": "23", "longitude": "-84.350139999999996", "latitude": "33.714779999999998", "occur_date": "10/20/2016", "type": "ROBBERY-PEDESTRIAN", "day": "Thu", "street_address": "1405 MORELAND AVE SE"}, {"neighborhood": "Custer/McDonough/Guice", "occur_time": "01", "longitude": "-84.349940000000004", "latitude": "33.709409999999998", "occur_date": "10/28/2016", "type": "AGG ASSAULT", "day": "Fri", "street_address": "1635 MORELAND AVE SE @FOXY LADY"}, {"neighborhood": "Custer/McDonough/Guice", "occur_time": "15", "longitude": "-84.358490000000003", "latitude": "33.709789999999998", "occur_date": "11/08/2016", "type": "LARCENY-NON VEHICLE", "day": "Tue", "street_address": "1940 FISHER RD SE"}, {"neighborhood": "Custer/McDonough/Guice", "occur_time": "20", "longitude": "-84.352109999999996", "latitude": "33.709910000000001", "occur_date": "11/11/2016", "type": "LARCENY-FROM VEHICLE", "day": "Sat", "street_address": "1634 WOODLAND AVE SE"}, {"neighborhood": "Custer/McDonough/Guice", "occur_time": "15", "longitude": "-84.358490000000003", "latitude": "33.709789999999998", "occur_date": "11/20/2016", "type": "AGG ASSAULT", "day": "Sun", "street_address": "1940 FISHER RD SE"}, {"neighborhood": "Custer/McDonough/Guice", "occur_time": "16", "longitude": "-84.358869999999996", "latitude": "33.708739999999999", "occur_date": "11/29/2016", "type": "LARCENY-NON VEHICLE", "day": "Tue", "street_address": "840 MCDONOUGH BLVD SE"}, {"neighborhood": "Custer/McDonough/Guice", "occur_time": "23", "longitude": "-84.355540000000005", "latitude": "33.708750000000002", "occur_date": "11/30/2016", "type": "ROBBERY-PEDESTRIAN", "day": "Wed", "street_address": "1021 MORELAND DR SE"}, {"neighborhood": "Custer/McDonough/Guice", "occur_time": "11", "longitude": "-84.358869999999996", "latitude": "33.708739999999999", "occur_date": "12/02/2016", "type": "LARCENY-FROM VEHICLE", "day": "Fri", "street_address": "840 MCDONOUGH BLVD SE"}, {"neighborhood": "Custer/McDonough/Guice", "occur_time": "22", "longitude": "-84.354789999999994", "latitude": "33.716560000000001", "occur_date": "12/07/2016", "type": "LARCENY-FROM VEHICLE", "day": "Thu", "street_address": "1034 CUSTER AVE SE"}, {"neighborhood": "Custer/McDonough/Guice", "occur_time": "10", "longitude": "-84.356740000000002", "latitude": "33.710340000000002", "occur_date": "12/16/2016", "type": "BURGLARY-RESIDENCE", "day": "Sat", "street_address": "1624 PONTIAC PL SE"}, {"neighborhood": "Custer/McDonough/Guice", "occur_time": "16", "longitude": "-84.358869999999996", "latitude": "33.708739999999999", "occur_date": "12/17/2016", "type": "AGG ASSAULT", "day": "Sat", "street_address": "840 MCDONOUGH BLVD"}, {"neighborhood": "Custer/McDonough/Guice", "occur_time": "19", "longitude": "-84.355130000000003", "latitude": "33.708730000000003", "occur_date": "12/24/2016", "type": "LARCENY-NON VEHICLE", "day": "Sat", "street_address": "1033 MORELAND DR SE"}, {"neighborhood": "Custer/McDonough/Guice", "occur_time": "03", "longitude": "-84.355000000000004", "latitude": "33.716700000000003", "occur_date": "12/25/2016", "type": "AUTO THEFT", "day": "Sun", "street_address": "1400 KNOB HILL CT SE"}, {"neighborhood": "Custer/McDonough/Guice", "occur_time": "01", "longitude": "-84.358490000000003", "latitude": "33.709789999999998", "occur_date": "12/28/2016", "type": "LARCENY-NON VEHICLE", "day": "Wed", "street_address": "1940 FISHER RD SE"}, {"neighborhood": "Custer/McDonough/Guice", "occur_time": "03", "longitude": "-84.350170000000006", "latitude": "33.711129999999997", "occur_date": "06/26/2016", "type": "HOMICIDE", "day": "Sun", "street_address": "1585 MORELAND AVE SE"}]