[{"neighborhood": "Lake Claire", "occur_time": "10", "longitude": "-84.318489999999997", "latitude": "33.764290000000003", "occur_date": "01/13/2016", "type": "LARCENY-FROM VEHICLE", "day": "Wed", "street_address": "2131 PALIFOX DR NE"}, {"neighborhood": "Lake Claire", "occur_time": "13", "longitude": "-84.324579999999997", "latitude": "33.763820000000003", "occur_date": "01/25/2016", "type": "AUTO THEFT", "day": "Mon", "street_address": "358 SOUTHERLAND TER NE"}, {"neighborhood": "Lake Claire", "occur_time": "12", "longitude": "-84.324860000000001", "latitude": "33.761180000000003", "occur_date": "01/28/2016", "type": "LARCENY-NON VEHICLE", "day": "Thu", "street_address": "1900 DEKALB AVE NE"}, {"neighborhood": "Lake Claire", "occur_time": "12", "longitude": "-84.328599999999994", "latitude": "33.760590000000001", "occur_date": "02/05/2016", "type": "LARCENY-NON VEHICLE", "day": "Unk", "street_address": "1798 DEKALB AVE NE"}, {"neighborhood": "Lake Claire", "occur_time": "16", "longitude": "-84.327680000000001", "latitude": "33.763910000000003", "occur_date": "02/11/2016", "type": "LARCENY-FROM VEHICLE", "day": "Thu", "street_address": "357 IVY PL NE"}, {"neighborhood": "Lake Claire", "occur_time": "13", "longitude": "-84.324060000000003", "latitude": "33.765949999999997", "occur_date": "02/16/2016", "type": "AUTO THEFT", "day": "Tue", "street_address": "430 CLAIRE DR NE"}, {"neighborhood": "Lake Claire", "occur_time": "07", "longitude": "-84.332359999999994", "latitude": "33.764240000000001", "occur_date": "02/21/2016", "type": "LARCENY-FROM VEHICLE", "day": "Sun", "street_address": "366 NELMS AVE NE"}, {"neighborhood": "Lake Claire", "occur_time": "02", "longitude": "-84.330640000000002", "latitude": "33.761890000000001", "occur_date": "02/20/2016", "type": "AUTO THEFT", "day": "Sat", "street_address": "280 ARIZONA AVE NE"}, {"neighborhood": "Lake Claire", "occur_time": "17", "longitude": "-84.321830000000006", "latitude": "33.764890000000001", "occur_date": "03/04/2016", "type": "BURGLARY-RESIDENCE", "day": "Fri", "street_address": "2006 MCLENDON AVE NE"}, {"neighborhood": "Lake Claire", "occur_time": "20", "longitude": "-84.320710000000005", "latitude": "33.762500000000003", "occur_date": "03/05/2016", "type": "BURGLARY-RESIDENCE", "day": "Sat", "street_address": "2040 DEKALB AVE NE"}, {"neighborhood": "Lake Claire", "occur_time": "16", "longitude": "-84.331239999999994", "latitude": "33.761879999999998", "occur_date": "03/10/2016", "type": "ROBBERY-PEDESTRIAN", "day": "Thu", "street_address": "270 ARIZONA AVE NE"}, {"neighborhood": "Lake Claire", "occur_time": "11", "longitude": "-84.330529999999996", "latitude": "33.761319999999998", "occur_date": "03/12/2016", "type": "ROBBERY-PEDESTRIAN", "day": "Sat", "street_address": "280 ARIZONA AVE NE"}, {"neighborhood": "Lake Claire", "occur_time": "11", "longitude": "-84.326539999999994", "latitude": "33.766030000000001", "occur_date": "03/12/2016", "type": "ROBBERY-PEDESTRIAN", "day": "Sat", "street_address": "430 LAKESHORE DR NE"}, {"neighborhood": "Lake Claire", "occur_time": "20", "longitude": "-84.325850000000003", "latitude": "33.760620000000003", "occur_date": "03/13/2016", "type": "LARCENY-FROM VEHICLE", "day": "Sun", "street_address": "240 HAMPTON TER NE"}, {"neighborhood": "Lake Claire", "occur_time": "15", "longitude": "-84.318860000000001", "latitude": "33.763759999999998", "occur_date": "03/11/2016", "type": "BURGLARY-RESIDENCE", "day": "Unk", "street_address": "2096 DEKALB AVE NE"}, {"neighborhood": "Lake Claire", "occur_time": "15", "longitude": "-84.318719999999999", "latitude": "33.763829999999999", "occur_date": "03/11/2016", "type": "BURGLARY-RESIDENCE", "day": "Unk", "street_address": "2100 DEKALB AVE NE"}, {"neighborhood": "Lake Claire", "occur_time": "12", "longitude": "-84.320710000000005", "latitude": "33.76267", "occur_date": "03/16/2016", "type": "LARCENY-NON VEHICLE", "day": "Wed", "street_address": "2044 DEKALB AVE NE"}, {"neighborhood": "Lake Claire", "occur_time": "21", "longitude": "-84.331010000000006", "latitude": "33.761510000000001", "occur_date": "03/17/2016", "type": "LARCENY-FROM VEHICLE", "day": "Thu", "street_address": "130 ARIZONA AVE NE"}, {"neighborhood": "Lake Claire", "occur_time": "21", "longitude": "-84.332719999999995", "latitude": "33.762239999999998", "occur_date": "04/13/2016", "type": "LARCENY-NON VEHICLE", "day": "Thu", "street_address": "1672 DEKALB AVE NE"}, {"neighborhood": "Lake Claire", "occur_time": "19", "longitude": "-84.332719999999995", "latitude": "33.762239999999998", "occur_date": "04/06/2016", "type": "LARCENY-NON VEHICLE", "day": "Wed", "street_address": "1672 DEKALB AVE NE"}, {"neighborhood": "Lake Claire", "occur_time": "17", "longitude": "-84.321119999999993", "latitude": "33.765160000000002", "occur_date": "05/12/2016", "type": "LARCENY-NON VEHICLE", "day": "Thu", "street_address": "2028 MCLENDON AVE NE"}, {"neighborhood": "Lake Claire", "occur_time": "10", "longitude": "-84.328659999999999", "latitude": "33.764189999999999", "occur_date": "05/18/2016", "type": "LARCENY-NON VEHICLE", "day": "Wed", "street_address": "362 CONNECTICUT AVE NE"}, {"neighborhood": "Lake Claire", "occur_time": "02", "longitude": "-84.327770000000001", "latitude": "33.764000000000003", "occur_date": "06/08/2016", "type": "LARCENY-FROM VEHICLE", "day": "Wed", "street_address": "367 IVY PL NE"}, {"neighborhood": "Lake Claire", "occur_time": "08", "longitude": "-84.325969999999998", "latitude": "33.76464", "occur_date": "06/10/2016", "type": "LARCENY-NON VEHICLE", "day": "Unk", "street_address": "1865 MCLENDON AVE NE"}, {"neighborhood": "Lake Claire", "occur_time": "10", "longitude": "-84.324169999999995", "latitude": "33.760539999999999", "occur_date": "07/18/2016", "type": "LARCENY-FROM VEHICLE", "day": "Mon", "street_address": "1932 DEKALB AVE NE"}, {"neighborhood": "Lake Claire", "occur_time": "13", "longitude": "-84.32535", "latitude": "33.767499999999998", "occur_date": "08/04/2016", "type": "BURGLARY-RESIDENCE", "day": "Thu", "street_address": "486 LAKESHORE DR NE"}, {"neighborhood": "Lake Claire", "occur_time": "00", "longitude": "-84.328789999999998", "latitude": "33.767580000000002", "occur_date": "09/13/2016", "type": "LARCENY-FROM VEHICLE", "day": "Tue", "street_address": "1794 MARLBROOK DR NE"}, {"neighborhood": "Lake Claire", "occur_time": "18", "longitude": "-84.331239999999994", "latitude": "33.764620000000001", "occur_date": "10/06/2016", "type": "BURGLARY-RESIDENCE", "day": "Unk", "street_address": "1719 MCLENDON AVE NE"}, {"neighborhood": "Lake Claire", "occur_time": "19", "longitude": "-84.330640000000002", "latitude": "33.761890000000001", "occur_date": "10/17/2016", "type": "AUTO THEFT", "day": "Tue", "street_address": "280 ARIZONA AVE NE"}, {"neighborhood": "Lake Claire", "occur_time": "12", "longitude": "-84.317089999999993", "latitude": "33.764589999999998", "occur_date": "10/25/2016", "type": "LARCENY-FROM VEHICLE", "day": "Tue", "street_address": "364 RIDGECREST RD NE"}, {"neighborhood": "Lake Claire", "occur_time": "02", "longitude": "-84.326989999999995", "latitude": "33.762549999999997", "occur_date": "11/15/2016", "type": "LARCENY-FROM VEHICLE", "day": "Tue", "street_address": "309 MATHEWS AVE NE"}, {"neighborhood": "Lake Claire", "occur_time": "19", "longitude": "-84.325090000000003", "latitude": "33.769629999999999", "occur_date": "11/28/2016", "type": "LARCENY-FROM VEHICLE", "day": "Tue", "street_address": "566 LAKESHORE DR NE"}, {"neighborhood": "Lake Claire", "occur_time": "19", "longitude": "-84.321920000000006", "latitude": "33.767400000000002", "occur_date": "11/30/2016", "type": "LARCENY-FROM VEHICLE", "day": "Wed", "street_address": "2006 PALIFOX DR NE"}, {"neighborhood": "Lake Claire", "occur_time": "21", "longitude": "-84.330950000000001", "latitude": "33.767740000000003", "occur_date": "12/05/2016", "type": "LARCENY-FROM VEHICLE", "day": "Tue", "street_address": "498 HAROLD AVE NE"}, {"neighborhood": "Lake Claire", "occur_time": "19", "longitude": "-84.325699999999998", "latitude": "33.766950000000001", "occur_date": "12/16/2016", "type": "AUTO THEFT", "day": "Sat", "street_address": "460 LAKESHORE DR NE"}, {"neighborhood": "Lake Claire", "occur_time": "22", "longitude": "-84.323440000000005", "latitude": "33.76773", "occur_date": "12/16/2016", "type": "LARCENY-FROM VEHICLE", "day": "Sat", "street_address": "495 CLAIRE DR NE"}]